[
    {
        "id": "1",
        "category": "Trending",
        "type": "Trending",
        "trending": "#GoibiboHostels",
        "posts": "N/A"
    },
    {
        "id": "2",
        "category": "Entertainment",
        "type": "Trending",
        "trending": "#Kannappa",
        "posts": "29.2K posts"
    },
    {
        "id": "3",
        "category": "Trending",
        "type": "Trending",
        "trending": "#DelhiGovtSchoolsShineInJEE",
        "posts": "1,916 posts"
    },
    {
        "id": "4",
        "category": "Trending",
        "type": "Trending",
        "trending": "#GlamUpFest2024",
        "posts": "7,246 posts"
    },
    {
        "id": "5",
        "category": "Entertainment",
        "type": "Trending",
        "trending": "#ChanduChampionInCinemas",
        "posts": "1,936 posts"
    },
    {
        "id": "6",
        "category": "Trending",
        "type": "Trending",
        "trending": "IIT-JEE",
        "posts": "1,345 posts"
    },
    {
        "id": "7",
        "category": "Trending",
        "type": "Trending",
        "trending": "End Halal Start Om Certificate",
        "posts": "1,316 posts"
    },
    {
        "id": "8",
        "category": "Trending",
        "type": "Trending",
        "trending": "AIMIM",
        "posts": "4,646 posts"
    },
    {
        "id": "9",
        "category": "Trending",
        "type": "Trending",
        "trending": "Science & Technology",
        "posts": "22.9K posts"
    },
    {
        "id": "10",
        "category": "Trending",
        "type": "Trending",
        "trending": "मुस्लिम महिला",
        "posts": "N/A"
    },
    {
        "id": "11",
        "category": "Politics",
        "type": "Trending",
        "trending": "शिक्षा मंत्री",
        "posts": "48.9K posts"
    },
    {
        "id": "12",
        "category": "Trending",
        "type": "Trending",
        "trending": "Panchayati Raj",
        "posts": "15.6K posts"
    },
    {
        "id": "13",
        "category": "Trending",
        "type": "Trending",
        "trending": "Vadodara",
        "posts": "17.6K posts"
    },
    {
        "id": "14",
        "category": "Politics",
        "type": "Trending",
        "trending": "Ukraine",
        "posts": "468K posts"
    },
    {
        "id": "15",
        "category": "Trending",
        "type": "Trending",
        "trending": "ध्रुव राठी",
        "posts": "51.2K posts"
    },
    {
        "id": "16",
        "category": "Celebrities",
        "type": "Trending",
        "trending": "सुशांत सिंह राजपूत",
        "posts": "8,961 posts"
    },
    {
        "id": "17",
        "category": "Trending",
        "type": "Trending",
        "trending": "Spain",
        "posts": "69.9K posts"
    },
    {
        "id": "18",
        "category": "K-pop",
        "type": "Trending",
        "trending": "JIN KOREA PRIDE",
        "posts": "111K posts"
    },
    {
        "id": "19",
        "category": "Trending",
        "type": "Trending",
        "trending": "Aurangabad",
        "posts": "1,657 posts"
    },
    {
        "id": "20",
        "category": "Trending",
        "type": "Trending",
        "trending": "Germany",
        "posts": "150K posts"
    },
    {
        "id": "21",
        "category": "Trending",
        "type": "Trending",
        "trending": "Dark Horse",
        "posts": "5,753 posts"
    },
    {
        "id": "22",
        "category": "Trending",
        "type": "Trending",
        "trending": "महाराष्ट्र सरकार",
        "posts": "42.6K posts"
    },
    {
        "id": "23",
        "category": "Trending",
        "type": "Trending",
        "trending": "Player of the Tournament",
        "posts": "7,767 posts"
    },
    {
        "id": "24",
        "category": "Cricket",
        "type": "Trending",
        "trending": "Sehwag",
        "posts": "3,329 posts"
    },
    {
        "id": "25",
        "category": "Trending",
        "type": "Trending",
        "trending": "NSUI",
        "posts": "7,899 posts"
    },
    {
        "id": "26",
        "category": "Business & finance",
        "type": "Trending",
        "trending": "TRAI",
        "posts": "56.5K posts"
    },
    {
        "id": "27",
        "category": "Football",
        "type": "Trending",
        "trending": "Golden Boot",
        "posts": "8,040 posts"
    },
    {
        "id": "28",
        "category": "Trending",
        "type": "Trending",
        "trending": "Flipkart",
        "posts": "14.2K posts"
    },
    {
        "id": "29",
        "category": "Trending",
        "type": "Trending",
        "trending": "portugal",
        "posts": "115K posts"
    },
    {
        "id": "30",
        "category": "Politics",
        "type": "Trending",
        "trending": "शिखर सम्मेलन",
        "posts": "5,242 posts"
    }
]